diwire/__init__.py
diwire/compiled_providers.py
diwire/container.py
diwire/container_context.py
diwire/container_helpers.py
diwire/container_injection.py
diwire/container_locks.py
diwire/container_resolution_stack.py
diwire/container_scopes.py
diwire/defaults.py
diwire/dependencies.py
diwire/exceptions.py
diwire/py.typed
diwire/registry.py
diwire/service_key.py
diwire/types.py
diwire/integrations/__init__.py
diwire/integrations/pydantic.py
diwire/integrations/pytest_plugin/README.rst
diwire/integrations/pytest_plugin/__init__.py
diwire/integrations/pytest_plugin/plugin.py
diwire-0.0.8.dist-info/METADATA
diwire-0.0.8.dist-info/WHEEL
diwire-0.0.8.dist-info/licenses/LICENSE
diwire-0.0.8.dist-info/RECORD
