Metadata-Version: 2.4
Name: diwire
Version: 0.0.8
Summary: A lightweight, type-safe dependency injection container with automatic wiring, scoped lifetimes, and zero dependencies
Project-URL: Homepage, https://github.com/maksimzayats/diwire
Project-URL: Documentation, https://docs.diwire.dev
Project-URL: Repository, https://github.com/maksimzayats/diwire
Project-URL: Issues, https://github.com/maksimzayats/diwire/issues
Author-email: Maksim Zayats <maksim@zayats.dev>
License-Expression: MIT
License-File: LICENSE
Keywords: autowiring,container,dependency-injection,di,inversion-of-control,ioc
Classifier: Development Status :: 3 - Alpha
Classifier: Intended Audience :: Developers
Classifier: Operating System :: OS Independent
Classifier: Programming Language :: Python :: 3
Classifier: Programming Language :: Python :: 3.10
Classifier: Programming Language :: Python :: 3.11
Classifier: Programming Language :: Python :: 3.12
Classifier: Programming Language :: Python :: 3.13
Classifier: Programming Language :: Python :: 3.14
Classifier: Programming Language :: Python :: Free Threading :: 3 - Stable
Classifier: Topic :: Software Development :: Libraries :: Python Modules
Classifier: Typing :: Typed
Requires-Python: >=3.10
